pheval_phen2gene/__init__.py
pheval_phen2gene/cli.py
pheval_phen2gene/cli_phen2gene.py
pheval_phen2gene/post_process/__init__.py
pheval_phen2gene/post_process/post_process.py
pheval_phen2gene/post_process/post_process_results_format.py
pheval_phen2gene/prepare/__init__.py
pheval_phen2gene/prepare/prepare_commands.py
pheval_phen2gene/prepare/prepare_inputs.py
pheval_phen2gene/run/__init__.py
pheval_phen2gene/run/run.py
pheval_phen2gene/runner.py
pheval_phen2gene/tool_specific_configuration_parser.py
pheval_phen2gene-0.2.2.dist-info/METADATA
pheval_phen2gene-0.2.2.dist-info/WHEEL
pheval_phen2gene-0.2.2.dist-info/entry_points.txt
pheval_phen2gene-0.2.2.dist-info/RECORD
