Metadata-Version: 2.3
Name: pheval-phen2gene
Version: 0.2.2
Summary: 
Author: Yasemin Bridges
Author-email: y.bridges@qmul.ac.uk
Requires-Python: >=3.10,<4.0.0
Classifier: Programming Language :: Python :: 3
Classifier: Programming Language :: Python :: 3.10
Classifier: Programming Language :: Python :: 3.11
Classifier: Programming Language :: Python :: 3.12
Classifier: Programming Language :: Python :: 3.13
Requires-Dist: click (>=8.1.3,<9.0.0)
Requires-Dist: docker (>=6.0.1,<7.0.0)
Requires-Dist: matplotlib (>=3.7.1,<4.0.0)
Requires-Dist: numpy (>=1.24.2,<2.0.0)
Requires-Dist: oaklib (>=0.5.6)
Requires-Dist: pandas (>=1.5.2,<2.0.0)
Requires-Dist: pheval (>=0.5.1,<0.6.0)
Requires-Dist: wheel (>=0.40.0,<0.41.0)
